rawjs2dict/__init__.py
rawjs2dict/acorn.js
rawjs2dict/main.py
rawjs2dict/transformers.py
rawjs2dict/utils.py
rawjs2dict-0.0.9.dist-info/LICENSE
rawjs2dict-0.0.9.dist-info/METADATA
rawjs2dict-0.0.9.dist-info/WHEEL
rawjs2dict-0.0.9.dist-info/RECORD
